pybullet_planning/__init__.py
pybullet_planning/__version__.py
pybullet_planning/interfaces/__init__.py
pybullet_planning/interfaces/control/__init__.py
pybullet_planning/interfaces/control/control.py
pybullet_planning/interfaces/debug_utils/__init__.py
pybullet_planning/interfaces/debug_utils/debug_utils.py
pybullet_planning/interfaces/env_manager/__init__.py
pybullet_planning/interfaces/env_manager/pose_transformation.py
pybullet_planning/interfaces/env_manager/savers.py
pybullet_planning/interfaces/env_manager/shape_creation.py
pybullet_planning/interfaces/env_manager/simulation.py
pybullet_planning/interfaces/env_manager/user_io.py
pybullet_planning/interfaces/geometry/__init__.py
pybullet_planning/interfaces/geometry/bounding_box.py
pybullet_planning/interfaces/geometry/camera.py
pybullet_planning/interfaces/geometry/mesh.py
pybullet_planning/interfaces/geometry/pointcloud.py
pybullet_planning/interfaces/geometry/polygon.py
pybullet_planning/interfaces/kinematics/__init__.py
pybullet_planning/interfaces/kinematics/ik_interface.py
pybullet_planning/interfaces/kinematics/ik_utils.py
pybullet_planning/interfaces/kinematics/reachability.py
pybullet_planning/interfaces/planner_interface/SE2_pose_motion_planning.py
pybullet_planning/interfaces/planner_interface/__init__.py
pybullet_planning/interfaces/planner_interface/cartesian_motion_planning.py
pybullet_planning/interfaces/planner_interface/dag_search.py
pybullet_planning/interfaces/planner_interface/joint_motion_planning.py
pybullet_planning/interfaces/planner_interface/ladder_graph.py
pybullet_planning/interfaces/planner_interface/nonholonomic_motion_planning.py
pybullet_planning/interfaces/robots/__init__.py
pybullet_planning/interfaces/robots/body.py
pybullet_planning/interfaces/robots/collision.py
pybullet_planning/interfaces/robots/dynamics.py
pybullet_planning/interfaces/robots/joint.py
pybullet_planning/interfaces/robots/link.py
pybullet_planning/interfaces/task_modeling/__init__.py
pybullet_planning_eaa-0.5.1.dist-info/AUTHORS.rst
pybullet_planning_eaa-0.5.1.dist-info/LICENSE
pybullet_planning_eaa-0.5.1.dist-info/METADATA
pybullet_planning_eaa-0.5.1.dist-info/WHEEL
pybullet_planning_eaa-0.5.1.dist-info/top_level.txt
pybullet_planning_eaa-0.5.1.dist-info/RECORD
